setup.py
pydatabase/__init__.py
pythondb.egg-info/PKG-INFO
pythondb.egg-info/SOURCES.txt
pythondb.egg-info/dependency_links.txt
pythondb.egg-info/not-zip-safe
pythondb.egg-info/top_level.txt