Metadata-Version: 1.0
Name: pythondb
Version: 1.6
Summary: A fully featured database creation and maintenance tool using raw Python.
Home-page: https://github.com/Jackojc/pydatabase
Author: Jack Clarke
Author-email: jackojc@gmail.com
License: MIT
Platform: UNKNOWN
